py_calendars/__init__.py
py_calendars/year_month.py
py_calendars-0.0.1.dist-info/LICENSE
py_calendars-0.0.1.dist-info/METADATA
py_calendars-0.0.1.dist-info/WHEEL
py_calendars-0.0.1.dist-info/top_level.txt
py_calendars-0.0.1.dist-info/RECORD
