Metadata-Version: 2.1
Name: py-calendars
Version: 0.0.1
Summary: To print the calendar design on the terminal 
Home-page: https://github.com/surajs123/pycalendar
Author: Suraj S
Author-email: www.surajsuraj7600@gmail.com
License: UNKNOWN
Platform: UNKNOWN
Classifier: Programming Language :: Python :: 3
Classifier: License :: OSI Approved :: MIT License
Classifier: Operating System :: OS Independent
Requires-Python: >=3.6
License-File: LICENSE
